dtocean_logistics/__init__.py
dtocean_logistics-3.0.1.dist-info/METADATA
dtocean_logistics-3.0.1.dist-info/WHEEL
dtocean_logistics-3.0.1.dist-info/RECORD
