Metadata-Version: 2.1
Name: dtocean-logistics
Version: 3.0.1
Summary: Logistics functions for the DTOcean installation and maintenance modules
Author: Mathew Topper
Author-email: damm_horse@yahoo.co.uk
Requires-Python: >=3.13,<4.0
Classifier: Programming Language :: Python :: 3
Classifier: Programming Language :: Python :: 3.13
